smsspammer/__init__.py
smsspammer/result.py
smsspammer/spammer.py
smsspammer-0.0.1.dist-info/licenses/LICENSE
smsspammer-0.0.1.dist-info/METADATA
smsspammer-0.0.1.dist-info/WHEEL
smsspammer-0.0.1.dist-info/top_level.txt
smsspammer-0.0.1.dist-info/RECORD
