Metadata-Version: 2.4
Name: smsspammer
Version: 0.0.1
Summary: SMS and Call spammer on Python
Author-email: nennneko5787 <h4369@nennneko5787.net>
Project-URL: Homepage, https://github.com/nennneko5787/smsspammer
Project-URL: Issues, https://github.com/nennneko5787/smsspammer/issues
Classifier: Programming Language :: Python :: 3
Classifier: License :: OSI Approved :: GNU Affero General Public License v3
Classifier: Operating System :: OS Independent
Classifier: Natural Language :: Japanese
Requires-Python: >=3.8
License-File: LICENSE
Requires-Dist: httpx
Requires-Dist: cryptography
Dynamic: license-file
